libs3/__init__.py
libs3/os.py
libs3/path.py
libs3/shutil.py
libs3-1.2.dist-info/METADATA
libs3-1.2.dist-info/WHEEL
libs3-1.2.dist-info/top_level.txt
libs3-1.2.dist-info/RECORD
