Metadata-Version: 2.1
Name: libs3
Version: 1.2
Summary: This is python implementation for for interacting with s3, with familier syntax
Home-page: https://github.com/pankajr141/libs3
Author: Pankaj Rawat
Author-email: pankajr141@gmail.com
License: UNKNOWN
Platform: UNKNOWN
Classifier: Programming Language :: Python :: 3
Classifier: License :: OSI Approved :: MIT License
Classifier: Operating System :: OS Independent
Requires-Dist: boto3
